{"protocol_info":
  { "pre_times": [20.791666666, 0, 20.791666666],
      "sim_times": [[ 3.6734693877, 5, 3.6734693877]],
      "params_to_change": {
        "venous_svc/v_inf": [[0, 0.0001, 0]]},
      "experiment_colors": ["r"],
      "experiment_labels": ["inf"]
  },
  "data_items": [
    { "variable": "flow aortic root",
    "name_for_plotting": "v_{AR}",
    "data_type": "constant",
    "operation": "mean",
    "operands":["aortic_root/v"],
    "unit": "m3_per_s",
    "weight": 1,
    "value": 0.000134,
    "std": 0.000001,
    "experiment_idx": 0,
    "subexperiment_idx": 0,
    "cost_type":"gaussian_MLE",
    "plot_type":"horizontal"
  },
  { "variable": "pressure aortic root",
    "name_for_plotting": "u_{AR}",
    "data_type": "constant",
    "operation": "mean",
    "operands":["aortic_root/u"],
    "unit": "J_per_m3",
    "weight": 1,
    "value": 7792.67,
    "std": 664.44,
    "experiment_idx": 0,
    "subexperiment_idx": 0,
    "cost_type":"gaussian_MLE",
    "plot_type":"horizontal"
  },
  { "variable": "pulse pressure",
    "name_for_plotting": "u_{ARpp}",
    "data_type": "constant",
    "operation": "max_minus_min",
    "operands":["aortic_root/u"],
    "unit": "J_per_m3",
    "weight": 1,
    "value": 5335.84,
    "std": 1694.92,
    "experiment_idx": 0,
    "subexperiment_idx": 0,
    "cost_type":"gaussian_MLE",
    "plot_type":"horizontal"
  },
  { "variable": "central venous pressure",
    "name_for_plotting": "p_{cvp}",
    "data_type": "constant",
    "operation": "mean",
    "operands":["heart/u_ra"],
    "unit": "J_per_m3",
    "weight": 2,
    "value": 1542.66,
    "std": 224.96,
    "experiment_idx": 0,
    "subexperiment_idx": 0,
    "cost_type":"gaussian_MLE",
    "plot_type":"horizontal"
  },
  { "variable": "flow aortic root",
    "name_for_plotting": "v_{AR}",
    "data_type": "constant",
    "operation": "mean",
    "operands":["aortic_root/v"],
    "unit": "m3_per_s",
    "weight": 0,
    "value": 0.000138,
    "std": 0.000001,
    "experiment_idx": 0,
    "subexperiment_idx": 1,
    "cost_type":"gaussian_MLE",
    "plot_type":"horizontal"
  },
  { "variable": "pressure aortic root",
    "name_for_plotting": "u_{AR}",
    "data_type": "constant",
    "operation": "mean",
    "operands":["aortic_root/u"],
    "unit": "J_per_m3",
    "weight": 0,
    "value": 11803.41,
    "std": 2372.58,
    "experiment_idx": 0,
    "subexperiment_idx": 1,
    "cost_type":"gaussian_MLE",
    "plot_type":"horizontal"
  },
  { "variable": "pulse pressure",
    "name_for_plotting": "u_{ARpp}",
    "data_type": "constant",
    "operation": "max_minus_min",
    "operands":["aortic_root/u"],
    "unit": "J_per_m3",
    "weight": 0,
    "value": 6701.65,
    "std": 3078.64,
    "experiment_idx": 0,
    "subexperiment_idx": 1,
    "cost_type":"gaussian_MLE",
    "plot_type":"horizontal"
  },
  { "variable": "central venous pressure",
    "name_for_plotting": "p_{cvp}",
    "data_type": "constant",
    "operation": "mean",
    "operands":["heart/u_ra"],
    "unit": "J_per_m3",
    "weight": 0,
    "value": 1542.66,
    "std": 224.96,
    "experiment_idx": 0,
    "subexperiment_idx": 1,
    "cost_type":"gaussian_MLE",
    "plot_type":"horizontal"
  },
  { "variable": "flow aortic root",
    "name_for_plotting": "v_{AR}",
    "data_type": "constant",
    "operation": "mean",
    "operands":["aortic_root/v"],
    "unit": "m3_per_s",
    "weight": 1,
    "value": 0.000138,
    "std": 0.000001,
    "experiment_idx": 0,
    "subexperiment_idx": 2,
    "cost_type":"gaussian_MLE",
    "plot_type":"horizontal"
  },
  { "variable": "pressure aortic root",
    "name_for_plotting": "u_{AR}",
    "data_type": "constant",
    "operation": "mean",
    "operands":["aortic_root/u"],
    "unit": "J_per_m3",
    "weight": 1,
    "value": 8050.84,
    "std": 1069.53,
    "experiment_idx": 0,
    "subexperiment_idx": 2,
    "cost_type":"gaussian_MLE",
    "plot_type":"horizontal"
  },
  { "variable": "pulse pressure",
    "name_for_plotting": "u_{ARpp}",
    "data_type": "constant",
    "operation": "max_minus_min",
    "operands":["aortic_root/u"],
    "unit": "J_per_m3",
    "weight": 1,
    "value": 8421.03,
    "std": 1067.27,
    "experiment_idx": 0,
    "subexperiment_idx": 2,
    "cost_type":"gaussian_MLE",
    "plot_type":"horizontal"
  },
  { "variable": "central venous pressure",
    "name_for_plotting": "p_{cvp}",
    "data_type": "constant",
    "operation": "mean",
    "operands":["heart/u_ra"],
    "unit": "J_per_m3",
    "weight": 2,
    "value": 1777.19,
    "std": 246.49,
    "experiment_idx": 0,
    "subexperiment_idx": 2,
    "cost_type":"gaussian_MLE",
    "plot_type":"horizontal"
  }
  ]
}


